prefect_monday/__init__.py
prefect_monday/_version.py
prefect_monday/account.py
prefect_monday/app_subscription.py
prefect_monday/apps_monetization_status.py
prefect_monday/assets.py
prefect_monday/boards.py
prefect_monday/complexity.py
prefect_monday/credentials.py
prefect_monday/graphql.py
prefect_monday/items.py
prefect_monday/items_by_column_values.py
prefect_monday/items_by_multiple_column_values.py
prefect_monday/me.py
prefect_monday/mutations.py
prefect_monday/tags.py
prefect_monday/teams.py
prefect_monday/updates.py
prefect_monday/users.py
prefect_monday/utils.py
prefect_monday/webhooks.py
prefect_monday/configs/mutation/add_file_to_column.json
prefect_monday/configs/mutation/add_file_to_update.json
prefect_monday/configs/mutation/add_subscribers_to_board.json
prefect_monday/configs/mutation/add_teams_to_workspace.json
prefect_monday/configs/mutation/add_users_to_workspace.json
prefect_monday/configs/mutation/archive_board.json
prefect_monday/configs/mutation/archive_group.json
prefect_monday/configs/mutation/archive_item.json
prefect_monday/configs/mutation/change_column_metadata.json
prefect_monday/configs/mutation/change_column_title.json
prefect_monday/configs/mutation/change_column_value.json
prefect_monday/configs/mutation/change_multiple_column_values.json
prefect_monday/configs/mutation/change_simple_column_value.json
prefect_monday/configs/mutation/clear_item_updates.json
prefect_monday/configs/mutation/complexity.json
prefect_monday/configs/mutation/create_board.json
prefect_monday/configs/mutation/create_column.json
prefect_monday/configs/mutation/create_group.json
prefect_monday/configs/mutation/create_item.json
prefect_monday/configs/mutation/create_notification.json
prefect_monday/configs/mutation/create_or_get_tag.json
prefect_monday/configs/mutation/create_subitem.json
prefect_monday/configs/mutation/create_update.json
prefect_monday/configs/mutation/create_webhook.json
prefect_monday/configs/mutation/create_workspace.json
prefect_monday-0.2.2.dist-info/LICENSE
prefect_monday-0.2.2.dist-info/METADATA
prefect_monday-0.2.2.dist-info/WHEEL
prefect_monday-0.2.2.dist-info/entry_points.txt
prefect_monday-0.2.2.dist-info/top_level.txt
prefect_monday-0.2.2.dist-info/RECORD
